Workbook

Sheet サマリー
A1: ふらっと 収支計画サマリー(単位:万円)
A2: 前提を変えるには「前提条件」シートの青字を編集してください。税・資金調達の返済・減価償却は未考慮。
A4: ■ 悲観シナリオ
B5: 1年目 | C5: 2年目 | D5: 3年目 | E5: 4年目 | F5: 5年目
A6: 売上 | B6: =SUM('月次_悲観'!C13:N13) | C6: =SUM('月次_悲観'!O13:Z13) | D6: =SUM('月次_悲観'!AA13:AL13) | E6: =SUM('月次_悲観'!AM13:AX13) | F6: =SUM('月次_悲観'!AY13:BJ13)
A7: 費用 | B7: =SUM('月次_悲観'!C25:N25) | C7: =SUM('月次_悲観'!O25:Z25) | D7: =SUM('月次_悲観'!AA25:AL25) | E7: =SUM('月次_悲観'!AM25:AX25) | F7: =SUM('月次_悲観'!AY25:BJ25)
A8: 営業利益 | B8: =SUM('月次_悲観'!C26:N26) | C8: =SUM('月次_悲観'!O26:Z26) | D8: =SUM('月次_悲観'!AA26:AL26) | E8: =SUM('月次_悲観'!AM26:AX26) | F8: =SUM('月次_悲観'!AY26:BJ26)
A9: 年度末 有料店舗数 | B9: ='月次_悲観'!N8 | C9: ='月次_悲観'!Z8 | D9: ='月次_悲観'!AL8 | E9: ='月次_悲観'!AX8 | F9: ='月次_悲観'!BJ8
A10: 年度末 累計損益(初期投資込) | B10: ='月次_悲観'!N27 | C10: ='月次_悲観'!Z27 | D10: ='月次_悲観'!AL27 | E10: ='月次_悲観'!AX27 | F10: ='月次_悲観'!BJ27
A11: 月次黒字化の月 | B11: =IFERROR(INDEX('月次_悲観'!C3:BJ3,MATCH(TRUE,INDEX('月次_悲観'!C26:BJ26>0,0),0)),"60か月以内に未達")
A12: 累計黒字化(投資回収)の月 | B12: =IFERROR(INDEX('月次_悲観'!C3:BJ3,MATCH(TRUE,INDEX('月次_悲観'!C27:BJ27>0,0),0)),"60か月以内に未達")
A13: 必要資金(累計赤字の最大値) | B13: =-MIN('月次_悲観'!C27:BJ27)
A15: ■ 標準シナリオ
B16: 1年目 | C16: 2年目 | D16: 3年目 | E16: 4年目 | F16: 5年目
A17: 売上 | B17: =SUM('月次_標準'!C13:N13) | C17: =SUM('月次_標準'!O13:Z13) | D17: =SUM('月次_標準'!AA13:AL13) | E17: =SUM('月次_標準'!AM13:AX13) | F17: =SUM('月次_標準'!AY13:BJ13)
A18: 費用 | B18: =SUM('月次_標準'!C25:N25) | C18: =SUM('月次_標準'!O25:Z25) | D18: =SUM('月次_標準'!AA25:AL25) | E18: =SUM('月次_標準'!AM25:AX25) | F18: =SUM('月次_標準'!AY25:BJ25)
A19: 営業利益 | B19: =SUM('月次_標準'!C26:N26) | C19: =SUM('月次_標準'!O26:Z26) | D19: =SUM('月次_標準'!AA26:AL26) | E19: =SUM('月次_標準'!AM26:AX26) | F19: =SUM('月次_標準'!AY26:BJ26)
A20: 年度末 有料店舗数 | B20: ='月次_標準'!N8 | C20: ='月次_標準'!Z8 | D20: ='月次_標準'!AL8 | E20: ='月次_標準'!AX8 | F20: ='月次_標準'!BJ8
A21: 年度末 累計損益(初期投資込) | B21: ='月次_標準'!N27 | C21: ='月次_標準'!Z27 | D21: ='月次_標準'!AL27 | E21: ='月次_標準'!AX27 | F21: ='月次_標準'!BJ27
A22: 月次黒字化の月 | B22: =IFERROR(INDEX('月次_標準'!C3:BJ3,MATCH(TRUE,INDEX('月次_標準'!C26:BJ26>0,0),0)),"60か月以内に未達")
A23: 累計黒字化(投資回収)の月 | B23: =IFERROR(INDEX('月次_標準'!C3:BJ3,MATCH(TRUE,INDEX('月次_標準'!C27:BJ27>0,0),0)),"60か月以内に未達")
A24: 必要資金(累計赤字の最大値) | B24: =-MIN('月次_標準'!C27:BJ27)
A26: ■ 楽観シナリオ
B27: 1年目 | C27: 2年目 | D27: 3年目 | E27: 4年目 | F27: 5年目
A28: 売上 | B28: =SUM('月次_楽観'!C13:N13) | C28: =SUM('月次_楽観'!O13:Z13) | D28: =SUM('月次_楽観'!AA13:AL13) | E28: =SUM('月次_楽観'!AM13:AX13) | F28: =SUM('月次_楽観'!AY13:BJ13)
A29: 費用 | B29: =SUM('月次_楽観'!C25:N25) | C29: =SUM('月次_楽観'!O25:Z25) | D29: =SUM('月次_楽観'!AA25:AL25) | E29: =SUM('月次_楽観'!AM25:AX25) | F29: =SUM('月次_楽観'!AY25:BJ25)
A30: 営業利益 | B30: =SUM('月次_楽観'!C26:N26) | C30: =SUM('月次_楽観'!O26:Z26) | D30: =SUM('月次_楽観'!AA26:AL26) | E30: =SUM('月次_楽観'!AM26:AX26) | F30: =SUM('月次_楽観'!AY26:BJ26)
A31: 年度末 有料店舗数 | B31: ='月次_楽観'!N8 | C31: ='月次_楽観'!Z8 | D31: ='月次_楽観'!AL8 | E31: ='月次_楽観'!AX8 | F31: ='月次_楽観'!BJ8
A32: 年度末 累計損益(初期投資込) | B32: ='月次_楽観'!N27 | C32: ='月次_楽観'!Z27 | D32: ='月次_楽観'!AL27 | E32: ='月次_楽観'!AX27 | F32: ='月次_楽観'!BJ27
A33: 月次黒字化の月 | B33: =IFERROR(INDEX('月次_楽観'!C3:BJ3,MATCH(TRUE,INDEX('月次_楽観'!C26:BJ26>0,0),0)),"60か月以内に未達")
A34: 累計黒字化(投資回収)の月 | B34: =IFERROR(INDEX('月次_楽観'!C3:BJ3,MATCH(TRUE,INDEX('月次_楽観'!C27:BJ27>0,0),0)),"60か月以内に未達")
A35: 必要資金(累計赤字の最大値) | B35: =-MIN('月次_楽観'!C27:BJ27)
A37: ■ 参考:元の事業計画(資料)
B38: 1年目 | C38: 2年目 | D38: 3年目
A39: 資料の売上 | B39: 17820 | C39: 63000 | D39: 126000
A40: 資料の条件で正しく計算した売上 | B40: 9720 | C40: 36000 | D40: 72000
A41: 資料の営業利益 | B41: 14140 | C41: 51340 | D41: 102680

Sheet 前提条件
A1: ふらっと 収支計画 前提条件(単位:万円。青字=入力値、変更すると全シートに反映)
A3: 項目 | B3: 単位 | C3: 悲観 | D3: 標準 | E3: 楽観 | F3: メモ
A4: 新規契約店/月 (1〜6か月目) | B4: 店 | C4: 3 | D4: 4 | E4: 6 | F4: トライアル開始数
A5: 新規契約店/月 (7〜12か月目) | B5: 店 | C5: 6 | D5: 8 | E5: 12
A6: 新規契約店/月 (13〜24か月目) | B6: 店 | C6: 10 | D6: 18 | E6: 30
A7: 新規契約店/月 (25か月目以降) | B7: 店 | C7: 15 | D7: 35 | E7: 60
A8: 月次解約率(有料店) | B8: % | C8: 0.05 | D8: 0.035 | E8: 0.025 | F8: 中小飲食店は3〜5%でも起こり得る
A9: スタンダード比率 | B9: % | C9: 0.75 | D9: 0.7 | E9: 0.6 | F9: 個人店は安価プランが中心
A10: プラス比率 | B10: % | C10: 0.18 | D10: 0.2 | E10: 0.25
A11: プレミアム比率 | B11: % | C11: =1-C9-C10 | D11: =1-D9-D10 | E11: =1-E9-E10 | F11: 自動計算
A12: スタンダード月額 | B12: 万円 | C12: 1 | D12: 1 | E12: 1 | F12: 資料と同じ
A13: プラス月額 | B13: 万円 | C13: 2.5 | D13: 2.5 | E13: 2.5
A14: プレミアム月額 | B14: 万円 | C14: 5 | D14: 5 | E14: 5
A15: 平均月額(ARPU) | B15: 万円 | C15: =(C9*C12+C10*C13+C11*C14) | D15: =(D9*D12+D10*D13+D11*D14) | E15: =(E9*E12+E10*E13+E11*E14) | F15: 自動計算。資料は2.7〜3.0万円
A16: 成功報酬の来店数/店/月 | B16: 人 | C16: 0 | D16: 8 | E16: 20 | F16: 本体収益に対し小さい上乗せ
A17: 成功報酬 単価 | B17: 万円 | C17: 0.015 | D17: 0.015 | E17: 0.015 | F17: 1人150円
A18: 決済手数料率 | B18: % | C18: 0.036 | D18: 0.036 | E18: 0.036 | F18: カード決済等
A19: 初期投資 | B19: 万円 | C19: 500 | D19: 500 | E19: 500 | F19: AI活用MVP。資料は730万円
A20: 創業者報酬 | B20: 万円/月 | C20: 25 | D20: 25 | E20: 25 | F20: 最低限
A21: エンジニア費 1年目 | B21: 万円/月 | C21: 30 | D21: 30 | E21: 30 | F21: AI開発+外部レビュー(半常勤)
A22: エンジニア費 2年目 | B22: 万円/月 | C22: 50 | D22: 50 | E22: 50
A23: エンジニア費 3年目以降 | B23: 万円/月 | C23: 100 | D23: 100 | E23: 100 | F23: 機能拡張・POS連携
A24: 営業1人あたり月間獲得店数 | B24: 店 | C24: 8 | D24: 8 | E24: 8
A25: 営業人件費(社保込) | B25: 万円/人月 | C25: 40 | D25: 40 | E25: 40
A26: 営業人員の開始月 | B26: 月 | C26: 4 | D26: 4 | E26: 4 | F26: それまでは創業者が営業
A27: CS1人あたり対応店数 | B27: 店 | C27: 150 | D27: 150 | E27: 150
A28: CS人件費 | B28: 万円/人月 | C28: 35 | D28: 35 | E28: 35
A29: CS開始月 | B29: 月 | C29: 7 | D29: 7 | E29: 7
A30: マーケティング費 1年目 | B30: 万円/月 | C30: 20 | D30: 20 | E30: 20
A31: マーケティング費 2年目 | B31: 万円/月 | C31: 40 | D31: 40 | E31: 40
A32: マーケティング費 3年目以降 | B32: 万円/月 | C32: 80 | D32: 80 | E32: 80
A33: 家賃 1年目 | B33: 万円/月 | C33: 5 | D33: 5 | E33: 5 | F33: コワーキング
A34: 家賃 2年目 | B34: 万円/月 | C34: 10 | D34: 10 | E34: 10
A35: 家賃 3年目以降 | B35: 万円/月 | C35: 20 | D35: 20 | E35: 20
A36: 法務・会計・雑費 | B36: 万円/月 | C36: 5 | D36: 5 | E36: 5
A37: サーバー・地図API 固定 | B37: 万円/月 | C37: 3 | D37: 3 | E37: 3
A38: サーバー・地図API 変動/店 | B38: 万円/店 | C38: 0.05 | D38: 0.05 | E38: 0.05 | F38: 500円/店

Sheet 月次_悲観
A1: 月次収支(悲観シナリオ、単位:万円)
A3: 月 | C3: 1 | D3: 2 | E3: 3 | F3: 4 | G3: 5 | H3: 6 | I3: 7 | J3: 8 | K3: 9 | L3: 10 | M3: 11 | N3: 12 | O3: 13 | P3: 14 | Q3: 15 | R3: 16 | S3: 17 | T3: 18 | U3: 19 | V3: 20 | W3: 21 | X3: 22 | Y3: 23 | Z3: 24 | AA3: 25 | AB3: 26 | AC3: 27 | AD3: 28 | AE3: 29 | AF3: 30 | AG3: 31 | AH3: 32 | AI3: 33 | AJ3: 34 | AK3: 35 | AL3: 36 | AM3: 37 | AN3: 38 | AO3: 39 | AP3: 40 | AQ3: 41 | AR3: 42 | AS3: 43 | AT3: 44 | AU3: 45 | AV3: 46 | AW3: 47 | AX3: 48 | AY3: 49 | AZ3: 50 | BA3: 51 | BB3: 52 | BC3: 53 | BD3: 54 | BE3: 55 | BF3: 56 | BG3: 57 | BH3: 58 | BI3: 59 | BJ3: 60
A4: 年 | C4: =ROUNDUP(C3/12,0) | D4: =ROUNDUP(D3/12,0) | E4: =ROUNDUP(E3/12,0) | F4: =ROUNDUP(F3/12,0) | G4: =ROUNDUP(G3/12,0) | H4: =ROUNDUP(H3/12,0) | I4: =ROUNDUP(I3/12,0) | J4: =ROUNDUP(J3/12,0) | ... BJ4: =ROUNDUP(BJ3/12,0)
A5: 新規契約店(トライアル開始) | C5: =IF(C3<=6,前提条件!$C$4,IF(C3<=12,前提条件!$C$5,IF(C3<=24,前提条件!$C$6,前提条件!$C$7))) | D5: =IF(D3<=6,前提条件!$C$4,IF(D3<=12,前提条件!$C$5,IF(D3<=24,前提条件!$C$6,前提条件!$C$7))) | E5: =IF(E3<=6,前提条件!$C$4,IF(E3<=12,前提条件!$C$5,IF(E3<=24,前提条件!$C$6,前提条件!$C$7))) | F5: =IF(F3<=6,前提条件!$C$4,IF(F3<=12,前提条件!$C$5,IF(F3<=24,前提条件!$C$6,前提条件!$C$7))) | G5: =IF(G3<=6,前提条件!$C$4,IF(G3<=12,前提条件!$C$5,IF(G3<=24,前提条件!$C$6,前提条件!$C$7))) | H5: =IF(H3<=6,前提条件!$C$4,IF(H3<=12,前提条件!$C$5,IF(H3<=24,前提条件!$C$6,前提条件!$C$7))) | I5: =IF(I3<=6,前提条件!$C$4,IF(I3<=12,前提条件!$C$5,IF(I3<=24,前提条件!$C$6,前提条件!$C$7))) | J5: =IF(J3<=6,前提条件!$C$4,IF(J3<=12,前提条件!$C$5,IF(J3<=24,前提条件!$C$6,前提条件!$C$7))) | ... BJ5: =IF(BJ3<=6,前提条件!$C$4,IF(BJ3<=12,前提条件!$C$5,IF(BJ3<=24,前提条件!$C$6,前提条件!$C$7)))
A6: 有料化(新規) | C6: 0 | D6: 0 | E6: 0 | F6: =C5 | G6: =D5 | H6: =E5 | I6: =F5 | J6: =G5 | K6: =H5 | L6: =I5 | M6: =J5 | ... BJ6: =BG5
A7: 解約 | C7: 0 | D7: =C8*前提条件!$C$8 | E7: =D8*前提条件!$C$8 | F7: =E8*前提条件!$C$8 | G7: =F8*前提条件!$C$8 | H7: =G8*前提条件!$C$8 | I7: =H8*前提条件!$C$8 | J7: =I8*前提条件!$C$8 | K7: =J8*前提条件!$C$8 | ... BJ7: =BI8*前提条件!$C$8
A8: 有料店舗数 | C8: =C6-C7 | D8: =C8+D6-D7 | E8: =D8+E6-E7 | F8: =E8+F6-F7 | G8: =F8+G6-G7 | H8: =G8+H6-H7 | I8: =H8+I6-I7 | J8: =I8+J6-J7 | K8: =J8+K6-K7 | ... BJ8: =BI8+BJ6-BJ7
A9: トライアル中店舗 | C9: =SUM(C5:C5) | D9: =SUM(C5:D5) | E9: =SUM(C5:E5) | F9: =SUM(D5:F5) | G9: =SUM(E5:G5) | H9: =SUM(F5:H5) | I9: =SUM(G5:I5) | J9: =SUM(H5:J5) | K9: =SUM(I5:K5) | L9: =SUM(J5:L5) | ... BJ9: =SUM(BH5:BJ5)
A10: 平均月額 | C10: =前提条件!$C$15 | D10: =前提条件!$C$15 | E10: =前提条件!$C$15 | F10: =前提条件!$C$15 | G10: =前提条件!$C$15 | H10: =前提条件!$C$15 | I10: =前提条件!$C$15 | J10: =前提条件!$C$15 | ... BJ10: =前提条件!$C$15
A11: サブスク売上 | C11: =C8*C10 | D11: =D8*D10 | E11: =E8*E10 | F11: =F8*F10 | G11: =G8*G10 | H11: =H8*H10 | I11: =I8*I10 | J11: =J8*J10 | ... BJ11: =BJ8*BJ10
A12: 成功報酬売上 | C12: =C8*前提条件!$C$16*前提条件!$C$17 | D12: =D8*前提条件!$C$16*前提条件!$C$17 | E12: =E8*前提条件!$C$16*前提条件!$C$17 | F12: =F8*前提条件!$C$16*前提条件!$C$17 | G12: =G8*前提条件!$C$16*前提条件!$C$17 | H12: =H8*前提条件!$C$16*前提条件!$C$17 | I12: =I8*前提条件!$C$16*前提条件!$C$17 | J12: =J8*前提条件!$C$16*前提条件!$C$17 | ... BJ12: =BJ8*前提条件!$C$16*前提条件!$C$17
A13: 売上合計 | C13: =C11+C12 | D13: =D11+D12 | E13: =E11+E12 | F13: =F11+F12 | G13: =G11+G12 | H13: =H11+H12 | I13: =I11+I12 | J13: =J11+J12 | ... BJ13: =BJ11+BJ12
A14: 決済手数料 | C14: =C13*前提条件!$C$18 | D14: =D13*前提条件!$C$18 | E14: =E13*前提条件!$C$18 | F14: =F13*前提条件!$C$18 | G14: =G13*前提条件!$C$18 | H14: =H13*前提条件!$C$18 | I14: =I13*前提条件!$C$18 | J14: =J13*前提条件!$C$18 | ... BJ14: =BJ13*前提条件!$C$18
A15: サーバー・地図API | C15: =前提条件!$C$37+前提条件!$C$38*(C8+C9) | D15: =前提条件!$C$37+前提条件!$C$38*(D8+D9) | E15: =前提条件!$C$37+前提条件!$C$38*(E8+E9) | F15: =前提条件!$C$37+前提条件!$C$38*(F8+F9) | G15: =前提条件!$C$37+前提条件!$C$38*(G8+G9) | H15: =前提条件!$C$37+前提条件!$C$38*(H8+H9) | I15: =前提条件!$C$37+前提条件!$C$38*(I8+I9) | J15: =前提条件!$C$37+前提条件!$C$38*(J8+J9) | ... BJ15: =前提条件!$C$37+前提条件!$C$38*(BJ8+BJ9)
A16: 創業者報酬 | C16: =前提条件!$C$20 | D16: =前提条件!$C$20 | E16: =前提条件!$C$20 | F16: =前提条件!$C$20 | G16: =前提条件!$C$20 | H16: =前提条件!$C$20 | I16: =前提条件!$C$20 | J16: =前提条件!$C$20 | ... BJ16: =前提条件!$C$20
A17: エンジニア費 | C17: =IF(C4=1,前提条件!$C$21,IF(C4=2,前提条件!$C$22,前提条件!$C$23)) | D17: =IF(D4=1,前提条件!$C$21,IF(D4=2,前提条件!$C$22,前提条件!$C$23)) | E17: =IF(E4=1,前提条件!$C$21,IF(E4=2,前提条件!$C$22,前提条件!$C$23)) | F17: =IF(F4=1,前提条件!$C$21,IF(F4=2,前提条件!$C$22,前提条件!$C$23)) | G17: =IF(G4=1,前提条件!$C$21,IF(G4=2,前提条件!$C$22,前提条件!$C$23)) | H17: =IF(H4=1,前提条件!$C$21,IF(H4=2,前提条件!$C$22,前提条件!$C$23)) | I17: =IF(I4=1,前提条件!$C$21,IF(I4=2,前提条件!$C$22,前提条件!$C$23)) | J17: =IF(J4=1,前提条件!$C$21,IF(J4=2,前提条件!$C$22,前提条件!$C$23)) | ... BJ17: =IF(BJ4=1,前提条件!$C$21,IF(BJ4=2,前提条件!$C$22,前提条件!$C$23))
A18: 営業人員(人) | C18: =IF(C3<前提条件!$C$26,0,ROUNDUP(C5/前提条件!$C$24,0)) | D18: =IF(D3<前提条件!$C$26,0,ROUNDUP(D5/前提条件!$C$24,0)) | E18: =IF(E3<前提条件!$C$26,0,ROUNDUP(E5/前提条件!$C$24,0)) | F18: =IF(F3<前提条件!$C$26,0,ROUNDUP(F5/前提条件!$C$24,0)) | G18: =IF(G3<前提条件!$C$26,0,ROUNDUP(G5/前提条件!$C$24,0)) | H18: =IF(H3<前提条件!$C$26,0,ROUNDUP(H5/前提条件!$C$24,0)) | I18: =IF(I3<前提条件!$C$26,0,ROUNDUP(I5/前提条件!$C$24,0)) | J18: =IF(J3<前提条件!$C$26,0,ROUNDUP(J5/前提条件!$C$24,0)) | ... BJ18: =IF(BJ3<前提条件!$C$26,0,ROUNDUP(BJ5/前提条件!$C$24,0))
A19: 営業人件費 | C19: =C18*前提条件!$C$25 | D19: =D18*前提条件!$C$25 | E19: =E18*前提条件!$C$25 | F19: =F18*前提条件!$C$25 | G19: =G18*前提条件!$C$25 | H19: =H18*前提条件!$C$25 | I19: =I18*前提条件!$C$25 | J19: =J18*前提条件!$C$25 | ... BJ19: =BJ18*前提条件!$C$25
A20: CS人員(人) | C20: =IF(C3<前提条件!$C$29,0,ROUNDUP(C8/前提条件!$C$27,0)) | D20: =IF(D3<前提条件!$C$29,0,ROUNDUP(D8/前提条件!$C$27,0)) | E20: =IF(E3<前提条件!$C$29,0,ROUNDUP(E8/前提条件!$C$27,0)) | F20: =IF(F3<前提条件!$C$29,0,ROUNDUP(F8/前提条件!$C$27,0)) | G20: =IF(G3<前提条件!$C$29,0,ROUNDUP(G8/前提条件!$C$27,0)) | H20: =IF(H3<前提条件!$C$29,0,ROUNDUP(H8/前提条件!$C$27,0)) | I20: =IF(I3<前提条件!$C$29,0,ROUNDUP(I8/前提条件!$C$27,0)) | J20: =IF(J3<前提条件!$C$29,0,ROUNDUP(J8/前提条件!$C$27,0)) | ... BJ20: =IF(BJ3<前提条件!$C$29,0,ROUNDUP(BJ8/前提条件!$C$27,0))
A21: CS人件費 | C21: =C20*前提条件!$C$28 | D21: =D20*前提条件!$C$28 | E21: =E20*前提条件!$C$28 | F21: =F20*前提条件!$C$28 | G21: =G20*前提条件!$C$28 | H21: =H20*前提条件!$C$28 | I21: =I20*前提条件!$C$28 | J21: =J20*前提条件!$C$28 | ... BJ21: =BJ20*前提条件!$C$28
A22: マーケティング費 | C22: =IF(C4=1,前提条件!$C$30,IF(C4=2,前提条件!$C$31,前提条件!$C$32)) | D22: =IF(D4=1,前提条件!$C$30,IF(D4=2,前提条件!$C$31,前提条件!$C$32)) | E22: =IF(E4=1,前提条件!$C$30,IF(E4=2,前提条件!$C$31,前提条件!$C$32)) | F22: =IF(F4=1,前提条件!$C$30,IF(F4=2,前提条件!$C$31,前提条件!$C$32)) | G22: =IF(G4=1,前提条件!$C$30,IF(G4=2,前提条件!$C$31,前提条件!$C$32)) | H22: =IF(H4=1,前提条件!$C$30,IF(H4=2,前提条件!$C$31,前提条件!$C$32)) | I22: =IF(I4=1,前提条件!$C$30,IF(I4=2,前提条件!$C$31,前提条件!$C$32)) | J22: =IF(J4=1,前提条件!$C$30,IF(J4=2,前提条件!$C$31,前提条件!$C$32)) | ... BJ22: =IF(BJ4=1,前提条件!$C$30,IF(BJ4=2,前提条件!$C$31,前提条件!$C$32))
A23: 家賃 | C23: =IF(C4=1,前提条件!$C$33,IF(C4=2,前提条件!$C$34,前提条件!$C$35)) | D23: =IF(D4=1,前提条件!$C$33,IF(D4=2,前提条件!$C$34,前提条件!$C$35)) | E23: =IF(E4=1,前提条件!$C$33,IF(E4=2,前提条件!$C$34,前提条件!$C$35)) | F23: =IF(F4=1,前提条件!$C$33,IF(F4=2,前提条件!$C$34,前提条件!$C$35)) | G23: =IF(G4=1,前提条件!$C$33,IF(G4=2,前提条件!$C$34,前提条件!$C$35)) | H23: =IF(H4=1,前提条件!$C$33,IF(H4=2,前提条件!$C$34,前提条件!$C$35)) | I23: =IF(I4=1,前提条件!$C$33,IF(I4=2,前提条件!$C$34,前提条件!$C$35)) | J23: =IF(J4=1,前提条件!$C$33,IF(J4=2,前提条件!$C$34,前提条件!$C$35)) | ... BJ23: =IF(BJ4=1,前提条件!$C$33,IF(BJ4=2,前提条件!$C$34,前提条件!$C$35))
A24: 法務・会計・雑費 | C24: =前提条件!$C$36 | D24: =前提条件!$C$36 | E24: =前提条件!$C$36 | F24: =前提条件!$C$36 | G24: =前提条件!$C$36 | H24: =前提条件!$C$36 | I24: =前提条件!$C$36 | J24: =前提条件!$C$36 | ... BJ24: =前提条件!$C$36
A25: 費用合計 | C25: =C14+C15+C16+C17+C19+C21+C22+C23+C24 | D25: =D14+D15+D16+D17+D19+D21+D22+D23+D24 | E25: =E14+E15+E16+E17+E19+E21+E22+E23+E24 | F25: =F14+F15+F16+F17+F19+F21+F22+F23+F24 | G25: =G14+G15+G16+G17+G19+G21+G22+G23+G24 | H25: =H14+H15+H16+H17+H19+H21+H22+H23+H24 | I25: =I14+I15+I16+I17+I19+I21+I22+I23+I24 | J25: =J14+J15+J16+J17+J19+J21+J22+J23+J24 | ... BJ25: =BJ14+BJ15+BJ16+BJ17+BJ19+BJ21+BJ22+BJ23+BJ24
A26: 営業利益 | C26: =C13-C25 | D26: =D13-D25 | E26: =E13-E25 | F26: =F13-F25 | G26: =G13-G25 | H26: =H13-H25 | I26: =I13-I25 | J26: =J13-J25 | ... BJ26: =BJ13-BJ25
A27: 累計損益(初期投資込) | C27: =-前提条件!$C$19+C26 | D27: =C27+D26 | E27: =D27+E26 | F27: =E27+F26 | G27: =F27+G26 | H27: =G27+H26 | I27: =H27+I26 | J27: =I27+J26 | K27: =J27+K26 | ... BJ27: =BI27+BJ26

Sheet 月次_標準
A1: 月次収支(標準シナリオ、単位:万円)
A3: 月 | C3: 1 | D3: 2 | E3: 3 | F3: 4 | G3: 5 | H3: 6 | I3: 7 | J3: 8 | K3: 9 | L3: 10 | M3: 11 | N3: 12 | O3: 13 | P3: 14 | Q3: 15 | R3: 16 | S3: 17 | T3: 18 | U3: 19 | V3: 20 | W3: 21 | X3: 22 | Y3: 23 | Z3: 24 | AA3: 25 | AB3: 26 | AC3: 27 | AD3: 28 | AE3: 29 | AF3: 30 | AG3: 31 | AH3: 32 | AI3: 33 | AJ3: 34 | AK3: 35 | AL3: 36 | AM3: 37 | AN3: 38 | AO3: 39 | AP3: 40 | AQ3: 41 | AR3: 42 | AS3: 43 | AT3: 44 | AU3: 45 | AV3: 46 | AW3: 47 | AX3: 48 | AY3: 49 | AZ3: 50 | BA3: 51 | BB3: 52 | BC3: 53 | BD3: 54 | BE3: 55 | BF3: 56 | BG3: 57 | BH3: 58 | BI3: 59 | BJ3: 60
A4: 年 | C4: =ROUNDUP(C3/12,0) | D4: =ROUNDUP(D3/12,0) | E4: =ROUNDUP(E3/12,0) | F4: =ROUNDUP(F3/12,0) | G4: =ROUNDUP(G3/12,0) | H4: =ROUNDUP(H3/12,0) | I4: =ROUNDUP(I3/12,0) | J4: =ROUNDUP(J3/12,0) | ... BJ4: =ROUNDUP(BJ3/12,0)
A5: 新規契約店(トライアル開始) | C5: =IF(C3<=6,前提条件!$D$4,IF(C3<=12,前提条件!$D$5,IF(C3<=24,前提条件!$D$6,前提条件!$D$7))) | D5: =IF(D3<=6,前提条件!$D$4,IF(D3<=12,前提条件!$D$5,IF(D3<=24,前提条件!$D$6,前提条件!$D$7))) | E5: =IF(E3<=6,前提条件!$D$4,IF(E3<=12,前提条件!$D$5,IF(E3<=24,前提条件!$D$6,前提条件!$D$7))) | F5: =IF(F3<=6,前提条件!$D$4,IF(F3<=12,前提条件!$D$5,IF(F3<=24,前提条件!$D$6,前提条件!$D$7))) | G5: =IF(G3<=6,前提条件!$D$4,IF(G3<=12,前提条件!$D$5,IF(G3<=24,前提条件!$D$6,前提条件!$D$7))) | H5: =IF(H3<=6,前提条件!$D$4,IF(H3<=12,前提条件!$D$5,IF(H3<=24,前提条件!$D$6,前提条件!$D$7))) | I5: =IF(I3<=6,前提条件!$D$4,IF(I3<=12,前提条件!$D$5,IF(I3<=24,前提条件!$D$6,前提条件!$D$7))) | J5: =IF(J3<=6,前提条件!$D$4,IF(J3<=12,前提条件!$D$5,IF(J3<=24,前提条件!$D$6,前提条件!$D$7))) | ... BJ5: =IF(BJ3<=6,前提条件!$D$4,IF(BJ3<=12,前提条件!$D$5,IF(BJ3<=24,前提条件!$D$6,前提条件!$D$7)))
A6: 有料化(新規) | C6: 0 | D6: 0 | E6: 0 | F6: =C5 | G6: =D5 | H6: =E5 | I6: =F5 | J6: =G5 | K6: =H5 | L6: =I5 | M6: =J5 | ... BJ6: =BG5
A7: 解約 | C7: 0 | D7: =C8*前提条件!$D$8 | E7: =D8*前提条件!$D$8 | F7: =E8*前提条件!$D$8 | G7: =F8*前提条件!$D$8 | H7: =G8*前提条件!$D$8 | I7: =H8*前提条件!$D$8 | J7: =I8*前提条件!$D$8 | K7: =J8*前提条件!$D$8 | ... BJ7: =BI8*前提条件!$D$8
A8: 有料店舗数 | C8: =C6-C7 | D8: =C8+D6-D7 | E8: =D8+E6-E7 | F8: =E8+F6-F7 | G8: =F8+G6-G7 | H8: =G8+H6-H7 | I8: =H8+I6-I7 | J8: =I8+J6-J7 | K8: =J8+K6-K7 | ... BJ8: =BI8+BJ6-BJ7
A9: トライアル中店舗 | C9: =SUM(C5:C5) | D9: =SUM(C5:D5) | E9: =SUM(C5:E5) | F9: =SUM(D5:F5) | G9: =SUM(E5:G5) | H9: =SUM(F5:H5) | I9: =SUM(G5:I5) | J9: =SUM(H5:J5) | K9: =SUM(I5:K5) | L9: =SUM(J5:L5) | ... BJ9: =SUM(BH5:BJ5)
A10: 平均月額 | C10: =前提条件!$D$15 | D10: =前提条件!$D$15 | E10: =前提条件!$D$15 | F10: =前提条件!$D$15 | G10: =前提条件!$D$15 | H10: =前提条件!$D$15 | I10: =前提条件!$D$15 | J10: =前提条件!$D$15 | ... BJ10: =前提条件!$D$15
A11: サブスク売上 | C11: =C8*C10 | D11: =D8*D10 | E11: =E8*E10 | F11: =F8*F10 | G11: =G8*G10 | H11: =H8*H10 | I11: =I8*I10 | J11: =J8*J10 | ... BJ11: =BJ8*BJ10
A12: 成功報酬売上 | C12: =C8*前提条件!$D$16*前提条件!$D$17 | D12: =D8*前提条件!$D$16*前提条件!$D$17 | E12: =E8*前提条件!$D$16*前提条件!$D$17 | F12: =F8*前提条件!$D$16*前提条件!$D$17 | G12: =G8*前提条件!$D$16*前提条件!$D$17 | H12: =H8*前提条件!$D$16*前提条件!$D$17 | I12: =I8*前提条件!$D$16*前提条件!$D$17 | J12: =J8*前提条件!$D$16*前提条件!$D$17 | ... BJ12: =BJ8*前提条件!$D$16*前提条件!$D$17
A13: 売上合計 | C13: =C11+C12 | D13: =D11+D12 | E13: =E11+E12 | F13: =F11+F12 | G13: =G11+G12 | H13: =H11+H12 | I13: =I11+I12 | J13: =J11+J12 | ... BJ13: =BJ11+BJ12
A14: 決済手数料 | C14: =C13*前提条件!$D$18 | D14: =D13*前提条件!$D$18 | E14: =E13*前提条件!$D$18 | F14: =F13*前提条件!$D$18 | G14: =G13*前提条件!$D$18 | H14: =H13*前提条件!$D$18 | I14: =I13*前提条件!$D$18 | J14: =J13*前提条件!$D$18 | ... BJ14: =BJ13*前提条件!$D$18
A15: サーバー・地図API | C15: =前提条件!$D$37+前提条件!$D$38*(C8+C9) | D15: =前提条件!$D$37+前提条件!$D$38*(D8+D9) | E15: =前提条件!$D$37+前提条件!$D$38*(E8+E9) | F15: =前提条件!$D$37+前提条件!$D$38*(F8+F9) | G15: =前提条件!$D$37+前提条件!$D$38*(G8+G9) | H15: =前提条件!$D$37+前提条件!$D$38*(H8+H9) | I15: =前提条件!$D$37+前提条件!$D$38*(I8+I9) | J15: =前提条件!$D$37+前提条件!$D$38*(J8+J9) | ... BJ15: =前提条件!$D$37+前提条件!$D$38*(BJ8+BJ9)
A16: 創業者報酬 | C16: =前提条件!$D$20 | D16: =前提条件!$D$20 | E16: =前提条件!$D$20 | F16: =前提条件!$D$20 | G16: =前提条件!$D$20 | H16: =前提条件!$D$20 | I16: =前提条件!$D$20 | J16: =前提条件!$D$20 | ... BJ16: =前提条件!$D$20
A17: エンジニア費 | C17: =IF(C4=1,前提条件!$D$21,IF(C4=2,前提条件!$D$22,前提条件!$D$23)) | D17: =IF(D4=1,前提条件!$D$21,IF(D4=2,前提条件!$D$22,前提条件!$D$23)) | E17: =IF(E4=1,前提条件!$D$21,IF(E4=2,前提条件!$D$22,前提条件!$D$23)) | F17: =IF(F4=1,前提条件!$D$21,IF(F4=2,前提条件!$D$22,前提条件!$D$23)) | G17: =IF(G4=1,前提条件!$D$21,IF(G4=2,前提条件!$D$22,前提条件!$D$23)) | H17: =IF(H4=1,前提条件!$D$21,IF(H4=2,前提条件!$D$22,前提条件!$D$23)) | I17: =IF(I4=1,前提条件!$D$21,IF(I4=2,前提条件!$D$22,前提条件!$D$23)) | J17: =IF(J4=1,前提条件!$D$21,IF(J4=2,前提条件!$D$22,前提条件!$D$23)) | ... BJ17: =IF(BJ4=1,前提条件!$D$21,IF(BJ4=2,前提条件!$D$22,前提条件!$D$23))
A18: 営業人員(人) | C18: =IF(C3<前提条件!$D$26,0,ROUNDUP(C5/前提条件!$D$24,0)) | D18: =IF(D3<前提条件!$D$26,0,ROUNDUP(D5/前提条件!$D$24,0)) | E18: =IF(E3<前提条件!$D$26,0,ROUNDUP(E5/前提条件!$D$24,0)) | F18: =IF(F3<前提条件!$D$26,0,ROUNDUP(F5/前提条件!$D$24,0)) | G18: =IF(G3<前提条件!$D$26,0,ROUNDUP(G5/前提条件!$D$24,0)) | H18: =IF(H3<前提条件!$D$26,0,ROUNDUP(H5/前提条件!$D$24,0)) | I18: =IF(I3<前提条件!$D$26,0,ROUNDUP(I5/前提条件!$D$24,0)) | J18: =IF(J3<前提条件!$D$26,0,ROUNDUP(J5/前提条件!$D$24,0)) | ... BJ18: =IF(BJ3<前提条件!$D$26,0,ROUNDUP(BJ5/前提条件!$D$24,0))
A19: 営業人件費 | C19: =C18*前提条件!$D$25 | D19: =D18*前提条件!$D$25 | E19: =E18*前提条件!$D$25 | F19: =F18*前提条件!$D$25 | G19: =G18*前提条件!$D$25 | H19: =H18*前提条件!$D$25 | I19: =I18*前提条件!$D$25 | J19: =J18*前提条件!$D$25 | ... BJ19: =BJ18*前提条件!$D$25
A20: CS人員(人) | C20: =IF(C3<前提条件!$D$29,0,ROUNDUP(C8/前提条件!$D$27,0)) | D20: =IF(D3<前提条件!$D$29,0,ROUNDUP(D8/前提条件!$D$27,0)) | E20: =IF(E3<前提条件!$D$29,0,ROUNDUP(E8/前提条件!$D$27,0)) | F20: =IF(F3<前提条件!$D$29,0,ROUNDUP(F8/前提条件!$D$27,0)) | G20: =IF(G3<前提条件!$D$29,0,ROUNDUP(G8/前提条件!$D$27,0)) | H20: =IF(H3<前提条件!$D$29,0,ROUNDUP(H8/前提条件!$D$27,0)) | I20: =IF(I3<前提条件!$D$29,0,ROUNDUP(I8/前提条件!$D$27,0)) | J20: =IF(J3<前提条件!$D$29,0,ROUNDUP(J8/前提条件!$D$27,0)) | ... BJ20: =IF(BJ3<前提条件!$D$29,0,ROUNDUP(BJ8/前提条件!$D$27,0))
A21: CS人件費 | C21: =C20*前提条件!$D$28 | D21: =D20*前提条件!$D$28 | E21: =E20*前提条件!$D$28 | F21: =F20*前提条件!$D$28 | G21: =G20*前提条件!$D$28 | H21: =H20*前提条件!$D$28 | I21: =I20*前提条件!$D$28 | J21: =J20*前提条件!$D$28 | ... BJ21: =BJ20*前提条件!$D$28
A22: マーケティング費 | C22: =IF(C4=1,前提条件!$D$30,IF(C4=2,前提条件!$D$31,前提条件!$D$32)) | D22: =IF(D4=1,前提条件!$D$30,IF(D4=2,前提条件!$D$31,前提条件!$D$32)) | E22: =IF(E4=1,前提条件!$D$30,IF(E4=2,前提条件!$D$31,前提条件!$D$32)) | F22: =IF(F4=1,前提条件!$D$30,IF(F4=2,前提条件!$D$31,前提条件!$D$32)) | G22: =IF(G4=1,前提条件!$D$30,IF(G4=2,前提条件!$D$31,前提条件!$D$32)) | H22: =IF(H4=1,前提条件!$D$30,IF(H4=2,前提条件!$D$31,前提条件!$D$32)) | I22: =IF(I4=1,前提条件!$D$30,IF(I4=2,前提条件!$D$31,前提条件!$D$32)) | J22: =IF(J4=1,前提条件!$D$30,IF(J4=2,前提条件!$D$31,前提条件!$D$32)) | ... BJ22: =IF(BJ4=1,前提条件!$D$30,IF(BJ4=2,前提条件!$D$31,前提条件!$D$32))
A23: 家賃 | C23: =IF(C4=1,前提条件!$D$33,IF(C4=2,前提条件!$D$34,前提条件!$D$35)) | D23: =IF(D4=1,前提条件!$D$33,IF(D4=2,前提条件!$D$34,前提条件!$D$35)) | E23: =IF(E4=1,前提条件!$D$33,IF(E4=2,前提条件!$D$34,前提条件!$D$35)) | F23: =IF(F4=1,前提条件!$D$33,IF(F4=2,前提条件!$D$34,前提条件!$D$35)) | G23: =IF(G4=1,前提条件!$D$33,IF(G4=2,前提条件!$D$34,前提条件!$D$35)) | H23: =IF(H4=1,前提条件!$D$33,IF(H4=2,前提条件!$D$34,前提条件!$D$35)) | I23: =IF(I4=1,前提条件!$D$33,IF(I4=2,前提条件!$D$34,前提条件!$D$35)) | J23: =IF(J4=1,前提条件!$D$33,IF(J4=2,前提条件!$D$34,前提条件!$D$35)) | ... BJ23: =IF(BJ4=1,前提条件!$D$33,IF(BJ4=2,前提条件!$D$34,前提条件!$D$35))
A24: 法務・会計・雑費 | C24: =前提条件!$D$36 | D24: =前提条件!$D$36 | E24: =前提条件!$D$36 | F24: =前提条件!$D$36 | G24: =前提条件!$D$36 | H24: =前提条件!$D$36 | I24: =前提条件!$D$36 | J24: =前提条件!$D$36 | ... BJ24: =前提条件!$D$36
A25: 費用合計 | C25: =C14+C15+C16+C17+C19+C21+C22+C23+C24 | D25: =D14+D15+D16+D17+D19+D21+D22+D23+D24 | E25: =E14+E15+E16+E17+E19+E21+E22+E23+E24 | F25: =F14+F15+F16+F17+F19+F21+F22+F23+F24 | G25: =G14+G15+G16+G17+G19+G21+G22+G23+G24 | H25: =H14+H15+H16+H17+H19+H21+H22+H23+H24 | I25: =I14+I15+I16+I17+I19+I21+I22+I23+I24 | J25: =J14+J15+J16+J17+J19+J21+J22+J23+J24 | ... BJ25: =BJ14+BJ15+BJ16+BJ17+BJ19+BJ21+BJ22+BJ23+BJ24
A26: 営業利益 | C26: =C13-C25 | D26: =D13-D25 | E26: =E13-E25 | F26: =F13-F25 | G26: =G13-G25 | H26: =H13-H25 | I26: =I13-I25 | J26: =J13-J25 | ... BJ26: =BJ13-BJ25
A27: 累計損益(初期投資込) | C27: =-前提条件!$D$19+C26 | D27: =C27+D26 | E27: =D27+E26 | F27: =E27+F26 | G27: =F27+G26 | H27: =G27+H26 | I27: =H27+I26 | J27: =I27+J26 | K27: =J27+K26 | ... BJ27: =BI27+BJ26

Sheet 月次_楽観
A1: 月次収支(楽観シナリオ、単位:万円)
A3: 月 | C3: 1 | D3: 2 | E3: 3 | F3: 4 | G3: 5 | H3: 6 | I3: 7 | J3: 8 | K3: 9 | L3: 10 | M3: 11 | N3: 12 | O3: 13 | P3: 14 | Q3: 15 | R3: 16 | S3: 17 | T3: 18 | U3: 19 | V3: 20 | W3: 21 | X3: 22 | Y3: 23 | Z3: 24 | AA3: 25 | AB3: 26 | AC3: 27 | AD3: 28 | AE3: 29 | AF3: 30 | AG3: 31 | AH3: 32 | AI3: 33 | AJ3: 34 | AK3: 35 | AL3: 36 | AM3: 37 | AN3: 38 | AO3: 39 | AP3: 40 | AQ3: 41 | AR3: 42 | AS3: 43 | AT3: 44 | AU3: 45 | AV3: 46 | AW3: 47 | AX3: 48 | AY3: 49 | AZ3: 50 | BA3: 51 | BB3: 52 | BC3: 53 | BD3: 54 | BE3: 55 | BF3: 56 | BG3: 57 | BH3: 58 | BI3: 59 | BJ3: 60
A4: 年 | C4: =ROUNDUP(C3/12,0) | D4: =ROUNDUP(D3/12,0) | E4: =ROUNDUP(E3/12,0) | F4: =ROUNDUP(F3/12,0) | G4: =ROUNDUP(G3/12,0) | H4: =ROUNDUP(H3/12,0) | I4: =ROUNDUP(I3/12,0) | J4: =ROUNDUP(J3/12,0) | ... BJ4: =ROUNDUP(BJ3/12,0)
A5: 新規契約店(トライアル開始) | C5: =IF(C3<=6,前提条件!$E$4,IF(C3<=12,前提条件!$E$5,IF(C3<=24,前提条件!$E$6,前提条件!$E$7))) | D5: =IF(D3<=6,前提条件!$E$4,IF(D3<=12,前提条件!$E$5,IF(D3<=24,前提条件!$E$6,前提条件!$E$7))) | E5: =IF(E3<=6,前提条件!$E$4,IF(E3<=12,前提条件!$E$5,IF(E3<=24,前提条件!$E$6,前提条件!$E$7))) | F5: =IF(F3<=6,前提条件!$E$4,IF(F3<=12,前提条件!$E$5,IF(F3<=24,前提条件!$E$6,前提条件!$E$7))) | G5: =IF(G3<=6,前提条件!$E$4,IF(G3<=12,前提条件!$E$5,IF(G3<=24,前提条件!$E$6,前提条件!$E$7))) | H5: =IF(H3<=6,前提条件!$E$4,IF(H3<=12,前提条件!$E$5,IF(H3<=24,前提条件!$E$6,前提条件!$E$7))) | I5: =IF(I3<=6,前提条件!$E$4,IF(I3<=12,前提条件!$E$5,IF(I3<=24,前提条件!$E$6,前提条件!$E$7))) | J5: =IF(J3<=6,前提条件!$E$4,IF(J3<=12,前提条件!$E$5,IF(J3<=24,前提条件!$E$6,前提条件!$E$7))) | ... BJ5: =IF(BJ3<=6,前提条件!$E$4,IF(BJ3<=12,前提条件!$E$5,IF(BJ3<=24,前提条件!$E$6,前提条件!$E$7)))
A6: 有料化(新規) | C6: 0 | D6: 0 | E6: 0 | F6: =C5 | G6: =D5 | H6: =E5 | I6: =F5 | J6: =G5 | K6: =H5 | L6: =I5 | M6: =J5 | ... BJ6: =BG5
A7: 解約 | C7: 0 | D7: =C8*前提条件!$E$8 | E7: =D8*前提条件!$E$8 | F7: =E8*前提条件!$E$8 | G7: =F8*前提条件!$E$8 | H7: =G8*前提条件!$E$8 | I7: =H8*前提条件!$E$8 | J7: =I8*前提条件!$E$8 | K7: =J8*前提条件!$E$8 | ... BJ7: =BI8*前提条件!$E$8
A8: 有料店舗数 | C8: =C6-C7 | D8: =C8+D6-D7 | E8: =D8+E6-E7 | F8: =E8+F6-F7 | G8: =F8+G6-G7 | H8: =G8+H6-H7 | I8: =H8+I6-I7 | J8: =I8+J6-J7 | K8: =J8+K6-K7 | ... BJ8: =BI8+BJ6-BJ7
A9: トライアル中店舗 | C9: =SUM(C5:C5) | D9: =SUM(C5:D5) | E9: =SUM(C5:E5) | F9: =SUM(D5:F5) | G9: =SUM(E5:G5) | H9: =SUM(F5:H5) | I9: =SUM(G5:I5) | J9: =SUM(H5:J5) | K9: =SUM(I5:K5) | L9: =SUM(J5:L5) | ... BJ9: =SUM(BH5:BJ5)
A10: 平均月額 | C10: =前提条件!$E$15 | D10: =前提条件!$E$15 | E10: =前提条件!$E$15 | F10: =前提条件!$E$15 | G10: =前提条件!$E$15 | H10: =前提条件!$E$15 | I10: =前提条件!$E$15 | J10: =前提条件!$E$15 | ... BJ10: =前提条件!$E$15
A11: サブスク売上 | C11: =C8*C10 | D11: =D8*D10 | E11: =E8*E10 | F11: =F8*F10 | G11: =G8*G10 | H11: =H8*H10 | I11: =I8*I10 | J11: =J8*J10 | ... BJ11: =BJ8*BJ10
A12: 成功報酬売上 | C12: =C8*前提条件!$E$16*前提条件!$E$17 | D12: =D8*前提条件!$E$16*前提条件!$E$17 | E12: =E8*前提条件!$E$16*前提条件!$E$17 | F12: =F8*前提条件!$E$16*前提条件!$E$17 | G12: =G8*前提条件!$E$16*前提条件!$E$17 | H12: =H8*前提条件!$E$16*前提条件!$E$17 | I12: =I8*前提条件!$E$16*前提条件!$E$17 | J12: =J8*前提条件!$E$16*前提条件!$E$17 | ... BJ12: =BJ8*前提条件!$E$16*前提条件!$E$17
A13: 売上合計 | C13: =C11+C12 | D13: =D11+D12 | E13: =E11+E12 | F13: =F11+F12 | G13: =G11+G12 | H13: =H11+H12 | I13: =I11+I12 | J13: =J11+J12 | ... BJ13: =BJ11+BJ12
A14: 決済手数料 | C14: =C13*前提条件!$E$18 | D14: =D13*前提条件!$E$18 | E14: =E13*前提条件!$E$18 | F14: =F13*前提条件!$E$18 | G14: =G13*前提条件!$E$18 | H14: =H13*前提条件!$E$18 | I14: =I13*前提条件!$E$18 | J14: =J13*前提条件!$E$18 | ... BJ14: =BJ13*前提条件!$E$18
A15: サーバー・地図API | C15: =前提条件!$E$37+前提条件!$E$38*(C8+C9) | D15: =前提条件!$E$37+前提条件!$E$38*(D8+D9) | E15: =前提条件!$E$37+前提条件!$E$38*(E8+E9) | F15: =前提条件!$E$37+前提条件!$E$38*(F8+F9) | G15: =前提条件!$E$37+前提条件!$E$38*(G8+G9) | H15: =前提条件!$E$37+前提条件!$E$38*(H8+H9) | I15: =前提条件!$E$37+前提条件!$E$38*(I8+I9) | J15: =前提条件!$E$37+前提条件!$E$38*(J8+J9) | ... BJ15: =前提条件!$E$37+前提条件!$E$38*(BJ8+BJ9)
A16: 創業者報酬 | C16: =前提条件!$E$20 | D16: =前提条件!$E$20 | E16: =前提条件!$E$20 | F16: =前提条件!$E$20 | G16: =前提条件!$E$20 | H16: =前提条件!$E$20 | I16: =前提条件!$E$20 | J16: =前提条件!$E$20 | ... BJ16: =前提条件!$E$20
A17: エンジニア費 | C17: =IF(C4=1,前提条件!$E$21,IF(C4=2,前提条件!$E$22,前提条件!$E$23)) | D17: =IF(D4=1,前提条件!$E$21,IF(D4=2,前提条件!$E$22,前提条件!$E$23)) | E17: =IF(E4=1,前提条件!$E$21,IF(E4=2,前提条件!$E$22,前提条件!$E$23)) | F17: =IF(F4=1,前提条件!$E$21,IF(F4=2,前提条件!$E$22,前提条件!$E$23)) | G17: =IF(G4=1,前提条件!$E$21,IF(G4=2,前提条件!$E$22,前提条件!$E$23)) | H17: =IF(H4=1,前提条件!$E$21,IF(H4=2,前提条件!$E$22,前提条件!$E$23)) | I17: =IF(I4=1,前提条件!$E$21,IF(I4=2,前提条件!$E$22,前提条件!$E$23)) | J17: =IF(J4=1,前提条件!$E$21,IF(J4=2,前提条件!$E$22,前提条件!$E$23)) | ... BJ17: =IF(BJ4=1,前提条件!$E$21,IF(BJ4=2,前提条件!$E$22,前提条件!$E$23))
A18: 営業人員(人) | C18: =IF(C3<前提条件!$E$26,0,ROUNDUP(C5/前提条件!$E$24,0)) | D18: =IF(D3<前提条件!$E$26,0,ROUNDUP(D5/前提条件!$E$24,0)) | E18: =IF(E3<前提条件!$E$26,0,ROUNDUP(E5/前提条件!$E$24,0)) | F18: =IF(F3<前提条件!$E$26,0,ROUNDUP(F5/前提条件!$E$24,0)) | G18: =IF(G3<前提条件!$E$26,0,ROUNDUP(G5/前提条件!$E$24,0)) | H18: =IF(H3<前提条件!$E$26,0,ROUNDUP(H5/前提条件!$E$24,0)) | I18: =IF(I3<前提条件!$E$26,0,ROUNDUP(I5/前提条件!$E$24,0)) | J18: =IF(J3<前提条件!$E$26,0,ROUNDUP(J5/前提条件!$E$24,0)) | ... BJ18: =IF(BJ3<前提条件!$E$26,0,ROUNDUP(BJ5/前提条件!$E$24,0))
A19: 営業人件費 | C19: =C18*前提条件!$E$25 | D19: =D18*前提条件!$E$25 | E19: =E18*前提条件!$E$25 | F19: =F18*前提条件!$E$25 | G19: =G18*前提条件!$E$25 | H19: =H18*前提条件!$E$25 | I19: =I18*前提条件!$E$25 | J19: =J18*前提条件!$E$25 | ... BJ19: =BJ18*前提条件!$E$25
A20: CS人員(人) | C20: =IF(C3<前提条件!$E$29,0,ROUNDUP(C8/前提条件!$E$27,0)) | D20: =IF(D3<前提条件!$E$29,0,ROUNDUP(D8/前提条件!$E$27,0)) | E20: =IF(E3<前提条件!$E$29,0,ROUNDUP(E8/前提条件!$E$27,0)) | F20: =IF(F3<前提条件!$E$29,0,ROUNDUP(F8/前提条件!$E$27,0)) | G20: =IF(G3<前提条件!$E$29,0,ROUNDUP(G8/前提条件!$E$27,0)) | H20: =IF(H3<前提条件!$E$29,0,ROUNDUP(H8/前提条件!$E$27,0)) | I20: =IF(I3<前提条件!$E$29,0,ROUNDUP(I8/前提条件!$E$27,0)) | J20: =IF(J3<前提条件!$E$29,0,ROUNDUP(J8/前提条件!$E$27,0)) | ... BJ20: =IF(BJ3<前提条件!$E$29,0,ROUNDUP(BJ8/前提条件!$E$27,0))
A21: CS人件費 | C21: =C20*前提条件!$E$28 | D21: =D20*前提条件!$E$28 | E21: =E20*前提条件!$E$28 | F21: =F20*前提条件!$E$28 | G21: =G20*前提条件!$E$28 | H21: =H20*前提条件!$E$28 | I21: =I20*前提条件!$E$28 | J21: =J20*前提条件!$E$28 | ... BJ21: =BJ20*前提条件!$E$28
A22: マーケティング費 | C22: =IF(C4=1,前提条件!$E$30,IF(C4=2,前提条件!$E$31,前提条件!$E$32)) | D22: =IF(D4=1,前提条件!$E$30,IF(D4=2,前提条件!$E$31,前提条件!$E$32)) | E22: =IF(E4=1,前提条件!$E$30,IF(E4=2,前提条件!$E$31,前提条件!$E$32)) | F22: =IF(F4=1,前提条件!$E$30,IF(F4=2,前提条件!$E$31,前提条件!$E$32)) | G22: =IF(G4=1,前提条件!$E$30,IF(G4=2,前提条件!$E$31,前提条件!$E$32)) | H22: =IF(H4=1,前提条件!$E$30,IF(H4=2,前提条件!$E$31,前提条件!$E$32)) | I22: =IF(I4=1,前提条件!$E$30,IF(I4=2,前提条件!$E$31,前提条件!$E$32)) | J22: =IF(J4=1,前提条件!$E$30,IF(J4=2,前提条件!$E$31,前提条件!$E$32)) | ... BJ22: =IF(BJ4=1,前提条件!$E$30,IF(BJ4=2,前提条件!$E$31,前提条件!$E$32))
A23: 家賃 | C23: =IF(C4=1,前提条件!$E$33,IF(C4=2,前提条件!$E$34,前提条件!$E$35)) | D23: =IF(D4=1,前提条件!$E$33,IF(D4=2,前提条件!$E$34,前提条件!$E$35)) | E23: =IF(E4=1,前提条件!$E$33,IF(E4=2,前提条件!$E$34,前提条件!$E$35)) | F23: =IF(F4=1,前提条件!$E$33,IF(F4=2,前提条件!$E$34,前提条件!$E$35)) | G23: =IF(G4=1,前提条件!$E$33,IF(G4=2,前提条件!$E$34,前提条件!$E$35)) | H23: =IF(H4=1,前提条件!$E$33,IF(H4=2,前提条件!$E$34,前提条件!$E$35)) | I23: =IF(I4=1,前提条件!$E$33,IF(I4=2,前提条件!$E$34,前提条件!$E$35)) | J23: =IF(J4=1,前提条件!$E$33,IF(J4=2,前提条件!$E$34,前提条件!$E$35)) | ... BJ23: =IF(BJ4=1,前提条件!$E$33,IF(BJ4=2,前提条件!$E$34,前提条件!$E$35))
A24: 法務・会計・雑費 | C24: =前提条件!$E$36 | D24: =前提条件!$E$36 | E24: =前提条件!$E$36 | F24: =前提条件!$E$36 | G24: =前提条件!$E$36 | H24: =前提条件!$E$36 | I24: =前提条件!$E$36 | J24: =前提条件!$E$36 | ... BJ24: =前提条件!$E$36
A25: 費用合計 | C25: =C14+C15+C16+C17+C19+C21+C22+C23+C24 | D25: =D14+D15+D16+D17+D19+D21+D22+D23+D24 | E25: =E14+E15+E16+E17+E19+E21+E22+E23+E24 | F25: =F14+F15+F16+F17+F19+F21+F22+F23+F24 | G25: =G14+G15+G16+G17+G19+G21+G22+G23+G24 | H25: =H14+H15+H16+H17+H19+H21+H22+H23+H24 | I25: =I14+I15+I16+I17+I19+I21+I22+I23+I24 | J25: =J14+J15+J16+J17+J19+J21+J22+J23+J24 | ... BJ25: =BJ14+BJ15+BJ16+BJ17+BJ19+BJ21+BJ22+BJ23+BJ24
A26: 営業利益 | C26: =C13-C25 | D26: =D13-D25 | E26: =E13-E25 | F26: =F13-F25 | G26: =G13-G25 | H26: =H13-H25 | I26: =I13-I25 | J26: =J13-J25 | ... BJ26: =BJ13-BJ25
A27: 累計損益(初期投資込) | C27: =-前提条件!$E$19+C26 | D27: =C27+D26 | E27: =D27+E26 | F27: =E27+F26 | G27: =F27+G26 | H27: =G27+H26 | I27: =H27+I26 | J27: =I27+J26 | K27: =J27+K26 | ... BJ27: =BI27+BJ26

Sheet 感度分析
A1: 標準シナリオの感度分析(Python計算値。前提条件を変えても自動更新されません)
A3: 月次黒字化する月(60か月以内)
A4: 月次解約率 \ 新規獲得ペース(標準比) | B4: ×0.5 | C4: ×0.75 | D4: ×1.0 | E4: ×1.25 | F4: ×1.5
A5: 2.0% | B5: 37 | C5: 32 | D5: 24 | E5: 21 | F5: 20
A6: 3.5% | B6: 40 | C6: 33 | D6: 30 | E6: 22 | F6: 21
A7: 5.0% | B7: 45 | C7: 35 | D7: 33 | E7: 23 | F7: 22
A8: 7.0% | B8: 未達 | C8: 40 | D8: 36 | E8: 33 | F8: 24
A10: 必要資金の目安(万円)
A11: 月次解約率 \ 新規獲得ペース(標準比) | B11: ×0.5 | C11: ×0.75 | D11: ×1.0 | E11: ×1.25 | F11: ×1.5
A12: 2.0% | B12: 5089 | C12: 3769 | D12: 3303 | E12: 2765 | F12: 2731
A13: 3.5% | B13: 5589 | C13: 4136 | D13: 3656 | E13: 3134 | F13: 2864
A14: 5.0% | B14: 6266 | C14: 4534 | D14: 4067 | E14: 3537 | F14: 3268
A15: 7.0% | B15: 7883 | C15: 5224 | D15: 4649 | E15: 4075 | F15: 3848
A17: 5年目の営業利益(万円)
A18: 月次解約率 \ 新規獲得ペース(標準比) | B18: ×0.5 | C18: ×0.75 | D18: ×1.0 | E18: ×1.25 | F18: ×1.5
A19: 2.0% | B19: 3345 | C19: 6743 | D19: 10141 | E19: 13539 | F19: 16972
A20: 3.5% | B20: 1679 | C20: 4366 | D20: 6984 | E20: 9566 | F20: 12184
A21: 5.0% | B21: 706 | C21: 2732 | D21: 4758 | E21: 6784 | F21: 8809
A22: 7.0% | B22: -465 | C22: 941 | D22: 2487 | E22: 4172 | F22: 5578
